Workbook

Sheet Commands
A1: Command | B1: Category | C1: Aliases | D1: Slash / Prefix / Both | E1: Description | F1: Arguments | G1: Required permissions | H1: Source bot(s) | I1: Uses buttons? | J1: Uses modal? | K1: Notes
A2: ?ban | B2: Moderation | C2: - | D2: Both | E2: Ban a member or a raw user ID, optionally for a fixed duration. | F2: <target> [duration] [reason] | G2: Moderator (or a mod role) | H2: Dyno, Carl-bot, Lawliet, Sapphire | I2: Yes | J2: No | K2: Confirm/cancel buttons locked to the invoker. Duration accepts 10m/2h/7d. Timed bans stored in the DB and lifted by a scheduler task. (moderation.py:441)
A3: ?banmessage | B3: Moderation | C3: - | D3: Prefix | E3: Set the DM sent to a member when they are banned. | F3: [message] | G3: Administrator (or an admin role) | H3: Carl-bot | I3: No | J3: Yes | K3: Modal for the message body; preview button before saving. (moderation.py:1969 Prefix-only by choice: configuration run once, kept out of the 100-slash budget. Reachable from ?config.)
A4: ?case | B4: Moderation | C4: - | D4: Both | E4: Show a single mod-log case in full. | F4: <number> | G4: Moderator (or a mod role) | H4: Dyno, Carl-bot | I4: No | J4: No | K4: - (moderation.py:1060)
A5: ?clearnotes | B5: Moderation | C5: - | D5: Prefix | E5: Delete every staff note on a member. | F5: <target> | G5: Administrator (or an admin role) | H5: Dyno | I5: Yes | J5: No | K5: Confirmation buttons. (moderation.py:1363 Prefix-only by choice: configuration run once, kept out of the 100-slash budget. Reachable from ?config.)
A6: ?clearwarns | B6: Moderation | C6: clearwarn | D6: Prefix | E6: Delete every warning on a member's record. | F6: <target> | G6: Administrator (or an admin role) | H6: Dyno, Carl-bot | I6: Yes | J6: No | K6: Destructive: confirm/cancel buttons required. (moderation.py:1026 Prefix-only by choice: configuration run once, kept out of the 100-slash budget. Reachable from ?config.)
A7: ?deafen | B7: Moderation | C7: undeafen | D7: Prefix | E7: Server-deafen or undeafen a member in voice. Toggles on current state. | F7: <target> [reason=No reason given] | G7: Moderator (or a mod role) | H7: Dyno | I7: No | J7: No | K7: One command, toggles based on current state. (moderation.py:1931 Prefix-only by choice: configuration run once, kept out of the 100-slash budget. Reachable from ?config.)
A8: ?delnote | B8: Moderation | C8: - | D8: Prefix | E8: Delete a single staff note by its ID. | F8: <note_id> | G8: Moderator (or a mod role) | H8: Dyno | I8: No | J8: No | K8: - (moderation.py:1350 Prefix-only by choice: configuration run once, kept out of the 100-slash budget. Reachable from ?config.)
A9: ?delwarn | B9: Moderation | C9: removewarn | D9: Both | E9: Delete a single warning by its ID. | F9: <warning_id> [reason=No reason given] | G9: Moderator (or a mod role) | H9: Dyno, Carl-bot | I9: No | J9: No | K9: - (moderation.py:994)
A10: ?duration | B10: Moderation | C10: - | D10: Prefix | E10: Change the remaining duration of an active mute or timed ban. | F10: <number> <new_duration> | G10: Moderator (or a mod role) | H10: Dyno | I10: No | J10: No | K10: - (moderation.py:1187 Prefix-only by choice: configuration run once, kept out of the 100-slash budget. Reachable from ?config.)
A11: ?kick | B11: Moderation | C11: - | D11: Both | E11: Remove a member from the server. They can rejoin with a new invite. | F11: <target> [reason=No reason given] | G11: Moderator (or a mod role) | H11: Dyno, Carl-bot, Lawliet, Sapphire | I11: Yes | J11: No | K11: Confirmation buttons. DM notice sent before the kick, failures reported but non-fatal. (moderation.py:759)
A12: ?lock | B12: Moderation | C12: - | D12: Both | E12: Deny Send Messages to @everyone in a channel. | F12: [channel] [duration] [reason] | G12: Moderator (or a mod role) | H12: Dyno, Carl-bot | I12: No | J12: No | K12: Stores the previous overwrite so ?unlock restores it exactly. (moderation.py:1518)
... A241: ?sync | B241: Owner / Operator | C241: - | D241: Prefix | E241: Re-register the application-command tree. | F241: [scope=guild] | G241: Bot owner | H241: Deezee original | I241: Yes | J241: No | K241: (owner.py:188 Prefix-only: never registered as a slash command.)

Sheet Summary
A1: Category | B1: Commands | C1: Uses buttons | D1: Uses modals | E1: Slash + prefix
A2: Moderation | B2: =COUNTIF(Commands!$B$2:$B$241,$A2) | C2: =COUNTIFS(Commands!$B$2:$B$241,$A2,Commands!$I$2:$I$241,"Yes") | D2: =COUNTIFS(Commands!$B$2:$B$241,$A2,Commands!$J$2:$J$241,"Yes") | E2: =COUNTIFS(Commands!$B$2:$B$241,$A2,Commands!$D$2:$D$241,"Both")
A3: Automod | B3: =COUNTIF(Commands!$B$2:$B$241,$A3) | C3: =COUNTIFS(Commands!$B$2:$B$241,$A3,Commands!$I$2:$I$241,"Yes") | D3: =COUNTIFS(Commands!$B$2:$B$241,$A3,Commands!$J$2:$J$241,"Yes") | E3: =COUNTIFS(Commands!$B$2:$B$241,$A3,Commands!$D$2:$D$241,"Both")
A4: Anti-raid & Verification | B4: =COUNTIF(Commands!$B$2:$B$241,$A4) | C4: =COUNTIFS(Commands!$B$2:$B$241,$A4,Commands!$I$2:$I$241,"Yes") | D4: =COUNTIFS(Commands!$B$2:$B$241,$A4,Commands!$J$2:$J$241,"Yes") | E4: =COUNTIFS(Commands!$B$2:$B$241,$A4,Commands!$D$2:$D$241,"Both")
A5: Roles & Reaction Roles | B5: =COUNTIF(Commands!$B$2:$B$241,$A5) | C5: =COUNTIFS(Commands!$B$2:$B$241,$A5,Commands!$I$2:$I$241,"Yes") | D5: =COUNTIFS(Commands!$B$2:$B$241,$A5,Commands!$J$2:$J$241,"Yes") | E5: =COUNTIFS(Commands!$B$2:$B$241,$A5,Commands!$D$2:$D$241,"Both")
A6: Logging | B6: =COUNTIF(Commands!$B$2:$B$241,$A6) | C6: =COUNTIFS(Commands!$B$2:$B$241,$A6,Commands!$I$2:$I$241,"Yes") | D6: =COUNTIFS(Commands!$B$2:$B$241,$A6,Commands!$J$2:$J$241,"Yes") | E6: =COUNTIFS(Commands!$B$2:$B$241,$A6,Commands!$D$2:$D$241,"Both")
A7: Leveling & Economy | B7: =COUNTIF(Commands!$B$2:$B$241,$A7) | C7: =COUNTIFS(Commands!$B$2:$B$241,$A7,Commands!$I$2:$I$241,"Yes") | D7: =COUNTIFS(Commands!$B$2:$B$241,$A7,Commands!$J$2:$J$241,"Yes") | E7: =COUNTIFS(Commands!$B$2:$B$241,$A7,Commands!$D$2:$D$241,"Both")
A8: Utility | B8: =COUNTIF(Commands!$B$2:$B$241,$A8) | C8: =COUNTIFS(Commands!$B$2:$B$241,$A8,Commands!$I$2:$I$241,"Yes") | D8: =COUNTIFS(Commands!$B$2:$B$241,$A8,Commands!$J$2:$J$241,"Yes") | E8: =COUNTIFS(Commands!$B$2:$B$241,$A8,Commands!$D$2:$D$241,"Both")
A9: Fun/Social | B9: =COUNTIF(Commands!$B$2:$B$241,$A9) | C9: =COUNTIFS(Commands!$B$2:$B$241,$A9,Commands!$I$2:$I$241,"Yes") | D9: =COUNTIFS(Commands!$B$2:$B$241,$A9,Commands!$J$2:$J$241,"Yes") | E9: =COUNTIFS(Commands!$B$2:$B$241,$A9,Commands!$D$2:$D$241,"Both")
A10: Giveaways & Events | B10: =COUNTIF(Commands!$B$2:$B$241,$A10) | C10: =COUNTIFS(Commands!$B$2:$B$241,$A10,Commands!$I$2:$I$241,"Yes") | D10: =COUNTIFS(Commands!$B$2:$B$241,$A10,Commands!$J$2:$J$241,"Yes") | E10: =COUNTIFS(Commands!$B$2:$B$241,$A10,Commands!$D$2:$D$241,"Both")
A11: Tags & Custom Commands | B11: =COUNTIF(Commands!$B$2:$B$241,$A11) | C11: =COUNTIFS(Commands!$B$2:$B$241,$A11,Commands!$I$2:$I$241,"Yes") | D11: =COUNTIFS(Commands!$B$2:$B$241,$A11,Commands!$J$2:$J$241,"Yes") | E11: =COUNTIFS(Commands!$B$2:$B$241,$A11,Commands!$D$2:$D$241,"Both")
A12: Server Config | B12: =COUNTIF(Commands!$B$2:$B$241,$A12) | C12: =COUNTIFS(Commands!$B$2:$B$241,$A12,Commands!$I$2:$I$241,"Yes") | D12: =COUNTIFS(Commands!$B$2:$B$241,$A12,Commands!$J$2:$J$241,"Yes") | E12: =COUNTIFS(Commands!$B$2:$B$241,$A12,Commands!$D$2:$D$241,"Both")
A13: Owner / Operator | B13: =COUNTIF(Commands!$B$2:$B$241,$A13) | C13: =COUNTIFS(Commands!$B$2:$B$241,$A13,Commands!$I$2:$I$241,"Yes") | D13: =COUNTIFS(Commands!$B$2:$B$241,$A13,Commands!$J$2:$J$241,"Yes") | E13: =COUNTIFS(Commands!$B$2:$B$241,$A13,Commands!$D$2:$D$241,"Both")
A14: TOTAL | B14: =SUM(B2:B13) | C14: =SUM(C2:C13) | D14: =SUM(D2:D13) | E14: =SUM(E2:E13)

Sheet Coverage
A1: Status | B1: Item | C1: Detail
A2: NOT BUILT | B2: (not built) VPN / proxy / Tor blocking | C2: Discord never exposes a member's IP to a bot. See the Notes sheet.
A3: BUILT AFTER THE SPEC | B3: ?filter | C3: Automod — Show every filter's current state. (automod.py:1071)
A4: BUILT AFTER THE SPEC | B4: ?autorole add | C4: Roles & Reaction Roles — Grant a role automatically on join, optionally after a delay. (roles.py:1523)
A5: BUILT AFTER THE SPEC | B5: ?autorole remove | C5: Roles & Reaction Roles — Stop granting a role on join. (roles.py:1568)
A6: BUILT AFTER THE SPEC | B6: ?reactionrole add | C6: Roles & Reaction Roles — Add one role to a menu. (roles.py:1152)
A7: BUILT AFTER THE SPEC | B7: ?reactionrole create | C7: Roles & Reaction Roles — Start a new role menu and open the builder. (roles.py:1118)
A8: BUILT AFTER THE SPEC | B8: ?reactionrole delete | C8: Roles & Reaction Roles — Delete a menu and, if it was published, its message. (roles.py:1244)
A9: BUILT AFTER THE SPEC | B9: ?reactionrole edit | C9: Roles & Reaction Roles — Reopen the builder for an existing menu. (roles.py:1139)
A10: BUILT AFTER THE SPEC | B10: ?reactionrole remove | C10: Roles & Reaction Roles — Remove one role from a menu. (roles.py:1187)
A11: BUILT AFTER THE SPEC | B11: ?selfroles add | C11: Roles & Reaction Roles — Mark a role as self-assignable. (roles.py:1909)
A12: BUILT AFTER THE SPEC | B12: ?selfroles remove | C12: Roles & Reaction Roles — Stop a role being self-assignable. (roles.py:1950)
... A56: BUILT AFTER THE SPEC | B56: ?sync | C56: Owner / Operator — Re-register the application-command tree. (owner.py:188)

Sheet Notes & Flags
A1: Topic | B1: Applies to | C1: Detail
A2: How this sheet is built | B2: tools/build_command_sheet.py | C2: The command list is parsed out of cogs/ with Python's ast module at build time -- it is not typed by hand and cannot drift from the code. Name, aliases, surface, arguments, permission gate and description all come from the source. Only 'Source bot(s)' and the leading half of 'Notes' are hand-written, because no amount of reading the code reveals which of the five original bots a command replaces. The Coverage sheet lists any disagreement between the original design spec and what actually exists. Regenerate with: python tools/build_command_sheet.py
A3: Buttons / modals columns | B3: Heuristic | C3: Unlike every other generated column, these two are inferred by looking for View(, confirm(, Paginator(, add_item(, send_modal( and Modal( in the function body. A command that builds its UI in a helper will read as No. Treat them as a hint, not a contract.
A4: Prefix | B4: ? | C4: Every command is registered as a prefix command. Mentioning the bot also works as a prefix, so a mistyped ?prefix can never lock the server out.
A5: Slash coverage | B5: 98 of 100 top-level | C5: NOT every command is a slash command. Discord caps a guild at 100 top-level application commands and this bot has far more than that, so 98 top-level commands are registered as slash and the rest are prefix-only. Subcommands of a slash group (?tag create, ?import levels) are slash too and do not count against the cap. The split is deliberate: slash goes to commands typed in a hurry or by ordinary members, prefix-only goes to configuration run once, whose discoverability is served by ?config. Commands whose arguments are long free text (tag bodies, embed content, ban lists) open a modal instead of taking a long option string.
A6: Slash commands not appearing | B6: Invite scope + GUILD_IDS | C6: Two causes, in order of likelihood. (1) The bot was invited without the applications.commands scope: tree.sync() then fails with 403 Missing Access, which core/bot.py logs as a warning and startup continues past. Re-invite with both scopes -- it does not remove the bot or reset anything. (2) The guild is not in GUILD_IDS: startup only syncs to guilds on that list, and ?sync iterates the same list, so running ?sync in an unlisted guild cannot help it. Check the boot log for 'Synced N command(s) to guild <id>' against 'Could not sync commands to guild <id>'.
A7: Deduplication | B7: 5 bots -> 1 | C7: Overlapping commands were collapsed. Example: Dyno ?ban, Carl-bot !ban, Lawliet L.ban and Sapphire s!ban all became a single ?ban; Carl-bot's eight separate text-transform commands became ?fancy <style>.
A8: No dashboard | B8: Hard constraint | C8: There is no web UI of any kind. ?config is the only configuration surface, built from embeds, buttons, select menus and modals.
A9: Persistent views | B9: bot.add_view() | C9: Reaction-role menus, giveaway entry buttons, verification buttons, poll buttons and suggestion vote buttons all use fixed custom_ids and are re-registered on ready, so they keep working after a restart.
A10: Confirmation pattern | B10: Destructive actions | C10: ban, softban, massban, kick, purge >100, nuke, lockdown, massrole, clearwarns, clearnotes, resetxp all, configreset and configimport require button confirmation. The view is locked to the invoker and times out after 30 seconds.
A11: EXTERNAL API - link scanning | B11: ?scanlinks | C11: Google Safe Browsing v5 urls:search, free and non-commercial-only. Endpoint GET https://safebrowsing.googleapis.com/v5/urls:search?key=<KEY>&urls=<url>, repeat the urls parameter for up to 50 URLs, empty request body. IMPORTANT: v5 responds with application/x-protobuf only; alt=json is rejected with 400 Unsupported Output Format. The response message is tiny and fixed (threats[] of {url, threatTypes[]}, plus cacheDuration), so the bot ships a ~40-line hand-written varint decoder rather than taking a protobuf dependency. An empty threats list means clean. Verified working against this project's key on 2026-08-07. Only unknown links are sent: a bundled trusted-domain database plus a per-guild trusted list are checked first, and verdicts are cached, so the API sees a small fraction of posted links. Set GOOGLE_SAFE_BROWSING_KEY in .env. Without it, the trusted lists and the offline phishing blocklist still work. Do not build against v4: it is deprecated and shuts down 31 March 2027.
A12: EXTERNAL API - fun content | B12: ?cat ?dog ?urban | C12: TheCatAPI, dog.ceo and Urban Dictionary. All free and keyless; each has a graceful failure path.
... A21: Scope | B21: Single server, per-guild schema | C21: Built for one guild, but every table is keyed by guild_id so a second server costs no migration.
